{
    "key": "group_600ef683bb5f3",
    "title": "Block: Team Cards",
    "fields": [
        {
            "key": "field_600ef8155107b",
            "label": "Team Bio Cards",
            "name": "team_bio_cards",
            "type": "repeater",
            "instructions": "",
            "required": 0,
            "conditional_logic": 0,
            "wrapper": {
                "width": "",
                "class": "",
                "id": ""
            },
            "collapsed": "",
            "min": 0,
            "max": 0,
            "layout": "block",
            "button_label": "Add Bio",
            "sub_fields": [
                {
                    "key": "field_600ef8295107c",
                    "label": "Image",
                    "name": "image",
                    "type": "image",
                    "instructions": "",
                    "required": 0,
                    "conditional_logic": 0,
                    "wrapper": {
                        "width": "",
                        "class": "",
                        "id": ""
                    },
                    "return_format": "id",
                    "preview_size": "medium",
                    "library": "all",
                    "min_width": "",
                    "min_height": "",
                    "min_size": "",
                    "max_width": "",
                    "max_height": "",
                    "max_size": "",
                    "mime_types": ""
                },
                {
                    "key": "field_600ef8345107d",
                    "label": "Name",
                    "name": "name",
                    "type": "text",
                    "instructions": "",
                    "required": 0,
                    "conditional_logic": 0,
                    "wrapper": {
                        "width": "50",
                        "class": "",
                        "id": ""
                    },
                    "default_value": "",
                    "placeholder": "",
                    "prepend": "",
                    "append": "",
                    "maxlength": ""
                },
                {
                    "key": "field_600ef8405107e",
                    "label": "Title",
                    "name": "title",
                    "type": "text",
                    "instructions": "",
                    "required": 0,
                    "conditional_logic": 0,
                    "wrapper": {
                        "width": "50",
                        "class": "",
                        "id": ""
                    },
                    "default_value": "",
                    "placeholder": "",
                    "prepend": "",
                    "append": "",
                    "maxlength": ""
                },
                {
                    "key": "field_600ef8465107f",
                    "label": "Content",
                    "name": "content",
                    "type": "wysiwyg",
                    "instructions": "Team member's bio content.",
                    "required": 0,
                    "conditional_logic": 0,
                    "wrapper": {
                        "width": "",
                        "class": "",
                        "id": ""
                    },
                    "default_value": "",
                    "tabs": "all",
                    "toolbar": "full",
                    "media_upload": 1,
                    "delay": 0
                },
                {
                    "key": "field_600ef85a51080",
                    "label": "Link Title",
                    "name": "link_title",
                    "type": "text",
                    "instructions": "Enter the link title for the link that will open full bio in a modal window. Example, View John's Bio.",
                    "required": 0,
                    "conditional_logic": 0,
                    "wrapper": {
                        "width": "",
                        "class": "",
                        "id": ""
                    },
                    "default_value": "",
                    "placeholder": "",
                    "prepend": "",
                    "append": "",
                    "maxlength": ""
                },
                {
                    "key": "field_600ef88c51081",
                    "label": "Enable Email",
                    "name": "enable_email",
                    "type": "true_false",
                    "instructions": "Do you want to add an email link for the team member?",
                    "required": 0,
                    "conditional_logic": 0,
                    "wrapper": {
                        "width": "",
                        "class": "",
                        "id": ""
                    },
                    "message": "",
                    "default_value": 0,
                    "ui": 1,
                    "ui_on_text": "",
                    "ui_off_text": ""
                },
                {
                    "key": "field_600ef8c151082",
                    "label": "Email Address",
                    "name": "email",
                    "type": "text",
                    "instructions": "Enter the email address for team member. Mailto attribute is automatically added to link.",
                    "required": 0,
                    "conditional_logic": [
                        [
                            {
                                "field": "field_600ef88c51081",
                                "operator": "==",
                                "value": "1"
                            }
                        ]
                    ],
                    "wrapper": {
                        "width": "50",
                        "class": "",
                        "id": ""
                    },
                    "default_value": "",
                    "placeholder": "",
                    "prepend": "",
                    "append": "",
                    "maxlength": ""
                },
                {
                    "key": "field_60104718b1be2",
                    "label": "Email Title",
                    "name": "email_title",
                    "type": "text",
                    "instructions": "Enter text for how email link is displayed. Example, team@email.com or Email Team.",
                    "required": 0,
                    "conditional_logic": [
                        [
                            {
                                "field": "field_600ef88c51081",
                                "operator": "==",
                                "value": "1"
                            }
                        ]
                    ],
                    "wrapper": {
                        "width": "50",
                        "class": "",
                        "id": ""
                    },
                    "default_value": "",
                    "placeholder": "",
                    "prepend": "",
                    "append": "",
                    "maxlength": ""
                }
            ]
        }
    ],
    "location": [
        [
            {
                "param": "block",
                "operator": "==",
                "value": "acf\/team-cards"
            }
        ]
    ],
    "menu_order": 0,
    "position": "normal",
    "style": "default",
    "label_placement": "top",
    "instruction_placement": "label",
    "hide_on_screen": "",
    "active": true,
    "description": "",
    "modified": 1622056924
}